Metadata-Version: 2.1
Name: library_architecture_mvvm_modify_python
Version: 1.0.1
Summary: MVVM Modify for Python but you can also port to another language
Home-page: https://github.com/antonpichka/library_architecture_mvvm_modify_python
Author: Anton Pichka
Author-email: antonpichka@gmail.com
Maintainer: Anton Pichka
Maintainer-email: antonpichka@gmail.com
License: MIT
License-File: LICENSE
